katonic/__init__.py
katonic/py.typed
katonic/version.py
katonic/connectors/__init__.py
katonic/connectors/python/__init__.py
katonic/connectors/python/azure_blob.py
katonic/connectors/python/bigquery.py
katonic/connectors/python/duckdb.py
katonic/connectors/python/mysql.py
katonic/connectors/python/postgres.py
katonic/connectors/python/redshift.py
katonic/connectors/python/s3.py
katonic/connectors/python/sap_hana.py
katonic/connectors/python/snowflake.py
katonic/drift/__init__.py
katonic/drift/adwin.py
katonic/drift/ddm.py
katonic/drift/eddm.py
katonic/drift/hddm_a.py
katonic/drift/hddm_w.py
katonic/drift/kswin.py
katonic/drift/page_hinkley.py
katonic/drift/target_drift.py
katonic/fe/__init__.py
katonic/fe/feature_creation.py
katonic/fe/feature_selection.py
katonic/fe/missing_value_treatment.py
katonic/fe/transformation.py
katonic/fe/univariate_selection.py
katonic/fe/variable_categorization.py
katonic/filemanager/__init__.py
katonic/filemanager/session.py
katonic/fs/__init__.py
katonic/fs/data_format.py
katonic/fs/data_source.py
katonic/fs/errors.py
katonic/fs/feature_store.py
katonic/fs/importer.py
katonic/fs/registry.py
katonic/fs/registry_store.py
katonic/fs/repo_config.py
katonic/fs/type_map.py
katonic/fs/utils.py
katonic/fs/value_type.py
katonic/fs/core/__init__.py
katonic/fs/core/passthrough_provider.py
katonic/fs/core/provider.py
katonic/fs/core/offline_stores/__init__.py
katonic/fs/core/offline_stores/dataframe_source.py
katonic/fs/core/offline_stores/file_source.py
katonic/fs/core/offline_stores/file_store.py
katonic/fs/core/offline_stores/offline_store.py
katonic/fs/core/offline_stores/offline_utils.py
katonic/fs/core/offline_stores/postgres_source.py
katonic/fs/core/offline_stores/postgres_store.py
katonic/fs/core/offline_stores/postgres_util.py
katonic/fs/core/online_stores/__init__.py
katonic/fs/core/online_stores/helpers.py
katonic/fs/core/online_stores/online_response.py
katonic/fs/core/online_stores/online_store.py
katonic-1.6.2.dist-info/LICENSE
katonic-1.6.2.dist-info/METADATA
katonic-1.6.2.dist-info/WHEEL
katonic-1.6.2.dist-info/top_level.txt
katonic-1.6.2.dist-info/RECORD
