Metadata-Version: 2.1
Name: katonic
Version: 1.6.2
Summary: A modern, enterprise-ready MLOps Python SDK
Home-page: https://www.katonic.ai/
Author: Katonic Pty Ltd.
Author-email: shailesh.kumar@katonic.ai
License: MIT
Project-URL: Documentation, https://docs.katonic.ai/
Platform: unix
Platform: linux
Platform: osx
Platform: cygwin
Platform: win32
Classifier: Programming Language :: Python :: 3.8
Classifier: Programming Language :: Python :: 3.9
Requires-Python: >=3.8
License-File: LICENSE
Requires-Dist: boto3 (==1.19.12)
Requires-Dist: LunarCalendar (>=0.0.9)
Requires-Dist: certifi (<2021.10.8,>=2017.4.17)
Requires-Dist: click (<8.1.2,>=7.1.1)
Requires-Dist: colorama
Requires-Dist: convertdate (>=2.1.2)
Requires-Dist: cron-descriptor
Requires-Dist: deprecation (<2.2.0,>=2.1.0)
Requires-Dist: func-timeout
Requires-Dist: greenlet (==1.1.1)
Requires-Dist: gunicorn (>=20.1.0)
Requires-Dist: humanize
Requires-Dist: importlib-metadata (==4.8.1)
Requires-Dist: isodate
Requires-Dist: markdown (>=3.0)
Requires-Dist: mlflow (==2.0.1)
Requires-Dist: msgpack (<1.1,>=1.0.0)
Requires-Dist: packaging (==21.2)
Requires-Dist: parsedatetime
Requires-Dist: protobuf (==3.19.4)
Requires-Dist: pyarrow (<6.1.0,>=6.0.0)
Requires-Dist: pydantic (==1.8.2)
Requires-Dist: pyparsing
Requires-Dist: python-dateutil
Requires-Dist: python-dotenv
Requires-Dist: python-geohash
Requires-Dist: pyyaml (<6,>=5.3)
Requires-Dist: requests (<2.26.0,>=2.10.0)
Requires-Dist: scikit-learn (==1.1.3)
Requires-Dist: tqdm (>=4.36.1)
Requires-Dist: typing-extensions (<4,>=3.10)
Requires-Dist: zipp (==3.5.0)
Provides-Extra: connector_azure
Requires-Dist: azure (<=4.0.0,>=3.0.0) ; extra == 'connector_azure'
Requires-Dist: pandas (<1.5.0,>=1.3.5) ; extra == 'connector_azure'
Provides-Extra: connector_bigquery
Requires-Dist: db-dtypes (==1.0.4) ; extra == 'connector_bigquery'
Requires-Dist: google-cloud-bigquery (==3.3.3) ; extra == 'connector_bigquery'
Provides-Extra: connector_duckdb
Requires-Dist: duckdb (==0.5.1) ; extra == 'connector_duckdb'
Provides-Extra: connector_mysql
Requires-Dist: mysql-connector-python (<=8.0.28,>=8.0.14) ; extra == 'connector_mysql'
Requires-Dist: pandas (<1.5.0,>=1.3.5) ; extra == 'connector_mysql'
Provides-Extra: connector_postgres
Requires-Dist: pandas (<1.5.0,>=1.3.5) ; extra == 'connector_postgres'
Requires-Dist: psycopg2-binary (<=2.9.3,>=2.8) ; extra == 'connector_postgres'
Provides-Extra: connector_redshift
Requires-Dist: redshift-connector (==2.0.909) ; extra == 'connector_redshift'
Provides-Extra: connector_saphana
Requires-Dist: hana-ml (==2.14.22092300) ; extra == 'connector_saphana'
Provides-Extra: connector_snowflake
Requires-Dist: pandas (<1.5.0,>=1.3.5) ; extra == 'connector_snowflake'
Requires-Dist: snowflake-connector-python[pandas] (<=2.7.6,>=2.0.0) ; extra == 'connector_snowflake'
Provides-Extra: connectors
Requires-Dist: azure (<=4.0.0,>=3.0.0) ; extra == 'connectors'
Requires-Dist: db-dtypes (==1.0.4) ; extra == 'connectors'
Requires-Dist: duckdb (==0.5.1) ; extra == 'connectors'
Requires-Dist: hana-ml (==2.14.22092300) ; extra == 'connectors'
Requires-Dist: google-cloud-bigquery (==3.3.3) ; extra == 'connectors'
Requires-Dist: mysql-connector-python (<=8.0.28,>=8.0.14) ; extra == 'connectors'
Requires-Dist: pandas (<1.5.0,>=1.3.5) ; extra == 'connectors'
Requires-Dist: psycopg2-binary (<=2.9.3,>=2.8) ; extra == 'connectors'
Requires-Dist: redshift-connector (==2.0.909) ; extra == 'connectors'
Requires-Dist: snowflake-connector-python[pandas] (<=2.7.6,>=2.0.0) ; extra == 'connectors'
Provides-Extra: drift
Requires-Dist: numpy (<1.24.0,>=1.19.0) ; extra == 'drift'
Requires-Dist: pandas (<1.5.0,>=1.3.5) ; extra == 'drift'
Requires-Dist: river (<=0.10.1,>=0.7.0) ; extra == 'drift'
Requires-Dist: scikit-learn (==1.1.3) ; extra == 'drift'
Requires-Dist: protobuf (==3.19.4) ; extra == 'drift'
Provides-Extra: fe
Requires-Dist: pandas (<1.5.0,>=1.3.5) ; extra == 'fe'
Requires-Dist: scikit-learn (==1.1.3) ; extra == 'fe'
Provides-Extra: filemanager
Requires-Dist: boto3 (>=1.19.12) ; extra == 'filemanager'
Requires-Dist: minio (<8.0,>7.0) ; extra == 'filemanager'
Provides-Extra: fs
Requires-Dist: Jinja2 (<4,>=2) ; extra == 'fs'
Requires-Dist: SQLAlchemy (<1.4.32,>=1.4.23) ; extra == 'fs'
Requires-Dist: delta (==0.4.2) ; extra == 'fs'
Requires-Dist: delta-spark (==1.0.0) ; extra == 'fs'
Requires-Dist: google (==3.0.0) ; extra == 'fs'
Requires-Dist: mmh3 (==3.0.0) ; extra == 'fs'
Requires-Dist: pandas (<1.5.0,>=1.3.5) ; extra == 'fs'
Requires-Dist: protobuf (==3.19.4) ; extra == 'fs'
Requires-Dist: psycopg2-binary (<2.9.3,>=2.9) ; extra == 'fs'
Requires-Dist: pyspark (==3.1.2) ; extra == 'fs'
Requires-Dist: redis (==3.5.3) ; extra == 'fs'
Requires-Dist: redis-py-cluster (==2.1.3) ; extra == 'fs'
Requires-Dist: starlette (==0.14.2) ; extra == 'fs'
Provides-Extra: ml
Requires-Dist: boto3 (==1.19.12) ; extra == 'ml'
Requires-Dist: catboost (==1.1) ; extra == 'ml'
Requires-Dist: cmdstanpy (==0.9.5) ; extra == 'ml'
Requires-Dist: lightgbm (==3.3.1) ; extra == 'ml'
Requires-Dist: matplotlib (<3.4.3,>=3.0.0) ; extra == 'ml'
Requires-Dist: mlflow (==2.0.1) ; extra == 'ml'
Requires-Dist: numpy (<1.24.0,>=1.19.0) ; extra == 'ml'
Requires-Dist: optuna (<2.10.0,>=2.8.0) ; extra == 'ml'
Requires-Dist: pandas (<1.5.0,>=1.3.5) ; extra == 'ml'
Requires-Dist: protobuf (==3.19.4) ; extra == 'ml'
Requires-Dist: python-dateutil (>=2.8.0) ; extra == 'ml'
Requires-Dist: scikit-learn (==1.1.3) ; extra == 'ml'
Requires-Dist: seaborn (==0.11.2) ; extra == 'ml'
Requires-Dist: tqdm (>=4.36.1) ; extra == 'ml'
Requires-Dist: xgboost (==1.5.0) ; extra == 'ml'
Provides-Extra: pipeline
Requires-Dist: kfp (<1.9,>0.1.10) ; extra == 'pipeline'
Requires-Dist: matplotlib (<3.4.3,>=3.0.0) ; extra == 'pipeline'
Requires-Dist: pandas (<1.5.0,>=1.3.5) ; extra == 'pipeline'
Requires-Dist: protobuf (==3.19.4) ; extra == 'pipeline'
Provides-Extra: testing
Requires-Dist: flake8 (>=3.9) ; extra == 'testing'
Requires-Dist: mypy (>=0.910) ; extra == 'testing'
Requires-Dist: pytest (>=6.0) ; extra == 'testing'
Requires-Dist: pytest-cov (>=2.0) ; extra == 'testing'
Requires-Dist: tox (>=3.24) ; extra == 'testing'
